fyers_api/__init__.py
fyers_api/accessToken.py
fyers_api/config.py
fyers_api/fyersFormation.py
fyers_api/fyersLog.py
fyers_api/fyersModel.py
fyers_api/fyersService.py
fyers_api/tesapi.py
fyers_api/Websocket/__init__.py
fyers_api/Websocket/constants.py
fyers_api/Websocket/ws.py
testapiv2-1.3.dist-info/LICENSE.txt
testapiv2-1.3.dist-info/METADATA
testapiv2-1.3.dist-info/WHEEL
testapiv2-1.3.dist-info/top_level.txt
testapiv2-1.3.dist-info/RECORD
