Metadata-Version: 2.1
Name: testapiv2
Version: 1.3
Summary: Fyers trading APIs.
Home-page: https://github.com/FyersDev/fyers-api-py
Author: vk
Author-email: support@fyers.in
License: UNKNOWN
Platform: UNKNOWN
Classifier: Programming Language :: Python :: 3
Classifier: License :: OSI Approved :: MIT License
Classifier: Operating System :: OS Independent
License-File: LICENSE.txt
Requires-Dist: requests (==2.25.1)
Requires-Dist: tornado (==6.1)
Requires-Dist: asyncio (==3.4.3)
Requires-Dist: websockets (==8.1)
Requires-Dist: websocket-client (==1.2.1)
